employee_info/__init__.py
employee_info/admin.py
employee_info/apps.py
employee_info/models.py
employee_info/load_data/LoadOrganisations.py
employee_info/load_data/__init__.py
employee_info/load_data/load_data.py
employee_info/load_data/load_functions.py
employee_info/load_data/load_resources.py
employee_info/management/commands/__init__.py
employee_info/management/commands/load_functions.py
employee_info/management/commands/load_organisations.py
employee_info/management/commands/load_resources.py
employee_info/migrations/0001_initial.py
employee_info/migrations/0002_organisation_set_null.py
employee_info/migrations/0003_description_null.py
employee_info/migrations/0004_employment_sequenceref.py
employee_info/migrations/0005_function_company_optional.py
employee_info/migrations/0006_company_name.py
employee_info/migrations/0007_resource_mainposition.py
employee_info/migrations/__init__.py
employee_info/static/employee_info/check.svg
employee_info/static/employee_info/cross.svg
employee_info/templates/employee_info/base.html
employee_info/templates/employee_info/boolean.html
employee_info/templates/employee_info/cost_center.html
employee_info/templates/employee_info/index.html
employee_info/templates/employee_info/organisation.html
employee_info/templates/employee_info/resource.html
employee_info/templates/employee_info/resource_form.html
employee_info/templates/employee_info/resource_list.html
employee_info/templates/employee_info/select_company.html
employee_info/templates/employee_info/select_cost_center.html
employee_info/templates/employee_info/select_organisation.html
employee_info/urls/__init__.py
employee_info/urls/autocomplete.py
employee_info/urls/browser.py
employee_info/urls/urls.py
employee_info/views/__init__.py
employee_info/views/autocomplete.py
employee_info/views/browser.py
tests/__init__.py
tests/test_settings.py
tests/tests.py
tests/test_data/TestData.py
tests/test_data/__init__.py
django_stamdata3-0.16.dist-info/LICENSE
django_stamdata3-0.16.dist-info/METADATA
django_stamdata3-0.16.dist-info/WHEEL
django_stamdata3-0.16.dist-info/top_level.txt
django_stamdata3-0.16.dist-info/RECORD
