Metadata-Version: 2.1
Name: django-stamdata3
Version: 0.16
Summary: A django app to import employee information from a stamdata3 XML file into a database
Home-page: https://github.com/StorFollo-IKT/django-stamdata3
Author: Anders Birkenes
Author-email: anders.birkenes@storfolloikt.no
License: GPL
Classifier: Framework :: Django
Classifier: Framework :: Django :: 2.1
Classifier: Intended Audience :: Developers
Classifier: License :: OSI Approved :: GNU General Public License v3 or later (GPLv3+)
Classifier: Operating System :: OS Independent
Classifier: Programming Language :: Python
Classifier: Programming Language :: Python :: 3.7
Classifier: Programming Language :: Python :: 3.8
License-File: LICENSE
Requires-Dist: django (<4,>=2)
Requires-Dist: stamdata3 (>=1.0)
Requires-Dist: requests
